mozpower/__init__.py
mozpower/intel_power_gadget.py
mozpower/macintelpower.py
mozpower/mozpower.py
mozpower/mozpowerutils.py
mozpower/powerbase.py
mozpower-1.1.2.dist-info/DESCRIPTION.rst
mozpower-1.1.2.dist-info/METADATA
mozpower-1.1.2.dist-info/RECORD
mozpower-1.1.2.dist-info/WHEEL
mozpower-1.1.2.dist-info/entry_points.txt
mozpower-1.1.2.dist-info/metadata.json
mozpower-1.1.2.dist-info/top_level.txt
